ctxgen/__init__.py
ctxgen/c.cp38-win32.pyd
ctxgen/generate.py
ctxseg/__init__.py
ctxseg/c.cp38-win32.pyd
ctxseg/metrics.py
ctxseg/seg_ttest.py
ctxseg/segment.py
ctxseg-0.1.4.dist-info/LICENSE
ctxseg-0.1.4.dist-info/METADATA
ctxseg-0.1.4.dist-info/WHEEL
ctxseg-0.1.4.dist-info/top_level.txt
ctxseg-0.1.4.dist-info/RECORD
