Metadata-Version: 2.1
Name: ctxseg
Version: 0.1.4
Summary: Official package for Segmentation by Context (CTX-SEG)
License-File: LICENSE
Requires-Dist: numpy
Requires-Dist: scipy
Requires-Dist: mne
